colcon_cargo/__init__.py
colcon_cargo/argcomplete_completer/__init__.py
colcon_cargo/argcomplete_completer/cargo_args.py
colcon_cargo/package_augmentation/__init__.py
colcon_cargo/package_augmentation/cargo.py
colcon_cargo/package_discovery/__init__.py
colcon_cargo/package_discovery/cargo_workspace.py
colcon_cargo/package_identification/__init__.py
colcon_cargo/package_identification/cargo.py
colcon_cargo/package_identification/cargo_workspace.py
colcon_cargo/task/__init__.py
colcon_cargo/task/cargo/__init__.py
colcon_cargo/task/cargo/build.py
colcon_cargo/task/cargo/test.py
colcon_cargo-0.2.0.dist-info/LICENSE
colcon_cargo-0.2.0.dist-info/METADATA
colcon_cargo-0.2.0.dist-info/WHEEL
colcon_cargo-0.2.0.dist-info/entry_points.txt
colcon_cargo-0.2.0.dist-info/top_level.txt
colcon_cargo-0.2.0.dist-info/zip-safe
colcon_cargo-0.2.0.dist-info/RECORD
