Metadata-Version: 2.1
Name: colcon-cargo
Version: 0.2.0
Summary: Extension for colcon to support cargo packages.
Home-page: UNKNOWN
Author: Gérald Lelong
Author-email: gerald.lelong@easymov.fr
Maintainer: Easymov Robotics
Maintainer-email: dev@easymov.fr
License: Apache License, Version 2.0
Keywords: colcon
Platform: UNKNOWN
Classifier: Development Status :: 3 - Alpha
Classifier: Environment :: Plugins
Classifier: Intended Audience :: Developers
Classifier: License :: OSI Approved :: Apache Software License
Classifier: Operating System :: MacOS
Classifier: Operating System :: Microsoft :: Windows
Classifier: Operating System :: POSIX
Classifier: Programming Language :: Python
Classifier: Topic :: Software Development :: Build Tools
Requires-Python: >=3.6
License-File: LICENSE
Requires-Dist: colcon-core (>=0.19.0)
Requires-Dist: tomli (>=1.0.0) ; python_version < "3.11"
Provides-Extra: test
Requires-Dist: flake8 (>=3.6.0) ; extra == 'test'
Requires-Dist: flake8-blind-except ; extra == 'test'
Requires-Dist: flake8-builtins ; extra == 'test'
Requires-Dist: flake8-class-newline ; extra == 'test'
Requires-Dist: flake8-comprehensions ; extra == 'test'
Requires-Dist: flake8-deprecated ; extra == 'test'
Requires-Dist: flake8-docstrings ; extra == 'test'
Requires-Dist: flake8-import-order ; extra == 'test'
Requires-Dist: flake8-quotes ; extra == 'test'
Requires-Dist: pep8-naming ; extra == 'test'
Requires-Dist: pylint ; extra == 'test'
Requires-Dist: pytest ; extra == 'test'
Requires-Dist: pytest-cov ; extra == 'test'
Requires-Dist: scspell3k (>=2.2) ; extra == 'test'
